iaccsept/__init__.py
iaccsept/perceptron.py
iaccsept_perceptron-0.0.4.dist-info/LICENSE
iaccsept_perceptron-0.0.4.dist-info/METADATA
iaccsept_perceptron-0.0.4.dist-info/WHEEL
iaccsept_perceptron-0.0.4.dist-info/top_level.txt
iaccsept_perceptron-0.0.4.dist-info/RECORD
