Metadata-Version: 2.1
Name: iaccsept-perceptron
Version: 0.0.4
Summary: Perceptron paper code
Author-email: Srikanta <srikantabiswal8093@gmail.com>
Project-URL: Homepage, https://github.com/Srikanta8596/iaccsept-perceptron-pkg
Project-URL: Bug Tracker, https://github.com/Srikanta8596/iaccsept-perceptron-pkg/issues
Classifier: Programming Language :: Python :: 3
Classifier: License :: OSI Approved :: MIT License
Classifier: Operating System :: OS Independent
Requires-Python: >=3.7
License-File: LICENSE
